XuXiangPythonSDK
